{
  "annotations": {
    "list": [
      {
        "builtIn": 1,
        "datasource": {
          "type": "grafana",
          "uid": "-- Grafana --"
        },
        "enable": true,
        "hide": true,
        "iconColor": "rgba(0, 211, 255, 1)",
        "name": "Annotations & Alerts",
        "target": {
          "limit": 100,
          "matchAny": false,
          "tags": [],
          "type": "dashboard"
        },
        "type": "dashboard"
      }
    ]
  },
  "editable": true,
  "fiscalYearStartMonth": 0,
  "graphTooltip": 0,
  "links": [],
  "liveNow": false,
  "panels": [
    {
      "gridPos": {
        "h": 1,
        "w": 24,
        "x": 0,
        "y": 0
      },
      "id": 52,
      "title": "Network / VPN",
      "type": "row"
    },
    {
      "datasource": {
        "type": "prometheus",
        "uid": "${datasource}"
      },
      "fieldConfig": {
        "defaults": {
          "color": {
            "mode": "thresholds"
          },
          "mappings": [],
          "max": 1,
          "min": 0,
          "thresholds": {
            "mode": "absolute",
            "steps": [
              {
                "color": "red",
                "value": null
              },
              {
                "color": "green",
                "value": 1
              }
            ]
          }
        },
        "overrides": []
      },
      "gridPos": {
        "h": 4,
        "w": 4,
        "x": 0,
        "y": 1
      },
      "id": 57,
      "options": {
        "colorMode": "background",
        "graphMode": "area",
        "justifyMode": "auto",
        "orientation": "auto",
        "reduceOptions": {
          "calcs": [
            "last"
          ],
          "fields": "",
          "values": false
        },
        "textMode": "auto"
      },
      "pluginVersion": "9.3.6",
      "targets": [
        {
          "datasource": {
            "type": "prometheus",
            "uid": "${datasource}"
          },
          "editorMode": "code",
          "expr": "quantile(0.95, probe_success{job=\"blackbox-icmp-vpn\",instance=~\"192.168.200.3\",location=\"ez\"}[5m])",
          "legendFormat": "DD",
          "range": true,
          "refId": "A"
        },
        {
          "datasource": {
            "type": "prometheus",
            "uid": "${datasource}"
          },
          "editorMode": "code",
          "expr": "quantile(0.95, probe_success{job=\"blackbox-icmp-vpn\",instance=~\"192.168.200.4\",location=\"ez\"}[5m])",
          "hide": false,
          "legendFormat": "PT",
          "range": true,
          "refId": "B"
        },
        {
          "datasource": {
            "type": "prometheus",
            "uid": "${datasource}"
          },
          "editorMode": "code",
          "expr": "quantile(0.95, probe_success{job=\"blackbox-icmp-vpn\",instance=~\"192.168.200.1\",location=\"ez\"}[5m])",
          "hide": false,
          "legendFormat": "RS",
          "range": true,
          "refId": "C"
        },
        {
          "datasource": {
            "type": "prometheus",
            "uid": "${datasource}"
          },
          "editorMode": "code",
          "expr": "quantile(0.95, probe_success{job=\"blackbox-icmp-vpn\",instance=~\"192.168.200.5\",location=\"ez\"}[5m])",
          "hide": false,
          "legendFormat": "SWISS",
          "range": true,
          "refId": "D"
        }
      ],
      "title": "VPN Health EZ",
      "type": "stat"
    },
    {
      "datasource": {
        "type": "prometheus",
        "uid": "${datasource}"
      },
      "fieldConfig": {
        "defaults": {
          "color": {
            "mode": "thresholds"
          },
          "mappings": [],
          "max": 1,
          "min": 0,
          "thresholds": {
            "mode": "absolute",
            "steps": [
              {
                "color": "red",
                "value": null
              },
              {
                "color": "green",
                "value": 1
              }
            ]
          }
        },
        "overrides": []
      },
      "gridPos": {
        "h": 4,
        "w": 4,
        "x": 4,
        "y": 1
      },
      "id": 53,
      "options": {
        "colorMode": "background",
        "graphMode": "area",
        "justifyMode": "auto",
        "orientation": "auto",
        "reduceOptions": {
          "calcs": [
            "last"
          ],
          "fields": "",
          "values": false
        },
        "textMode": "auto"
      },
      "pluginVersion": "9.3.6",
      "targets": [
        {
          "datasource": {
            "type": "prometheus",
            "uid": "${datasource}"
          },
          "editorMode": "code",
          "expr": "quantile(0.95, probe_success{job=\"blackbox-icmp-vpn\",instance=~\"192.168.200.2\",location=\"dd\"}[5m])",
          "legendFormat": "EZ",
          "range": true,
          "refId": "A"
        },
        {
          "datasource": {
            "type": "prometheus",
            "uid": "${datasource}"
          },
          "editorMode": "code",
          "expr": "quantile(0.95, probe_success{job=\"blackbox-icmp-vpn\",instance=~\"192.168.200.4\",location=\"dd\"}[5m])",
          "hide": false,
          "legendFormat": "PT",
          "range": true,
          "refId": "B"
        },
        {
          "datasource": {
            "type": "prometheus",
            "uid": "${datasource}"
          },
          "editorMode": "code",
          "expr": "quantile(0.95, probe_success{job=\"blackbox-icmp-vpn\",instance=~\"192.168.200.1\",location=\"dd\"}[5m])",
          "hide": false,
          "legendFormat": "RS",
          "range": true,
          "refId": "C"
        },
        {
          "datasource": {
            "type": "prometheus",
            "uid": "${datasource}"
          },
          "editorMode": "code",
          "expr": "quantile(0.95, probe_success{job=\"blackbox-icmp-vpn\",instance=~\"192.168.200.5\",location=\"dd\"}[5m])",
          "hide": false,
          "legendFormat": "SW",
          "range": true,
          "refId": "D"
        }
      ],
      "title": "VPN Health DD",
      "type": "stat"
    },
    {
      "datasource": {
        "type": "prometheus",
        "uid": "${datasource}"
      },
      "fieldConfig": {
        "defaults": {
          "color": {
            "mode": "thresholds"
          },
          "mappings": [],
          "max": 1,
          "min": 0,
          "thresholds": {
            "mode": "absolute",
            "steps": [
              {
                "color": "red",
                "value": null
              },
              {
                "color": "green",
                "value": 1
              }
            ]
          }
        },
        "overrides": []
      },
      "gridPos": {
        "h": 4,
        "w": 4,
        "x": 8,
        "y": 1
      },
      "id": 58,
      "options": {
        "colorMode": "background",
        "graphMode": "area",
        "justifyMode": "auto",
        "orientation": "auto",
        "reduceOptions": {
          "calcs": [
            "last"
          ],
          "fields": "",
          "values": false
        },
        "textMode": "auto"
      },
      "pluginVersion": "9.3.6",
      "targets": [
        {
          "datasource": {
            "type": "prometheus",
            "uid": "${datasource}"
          },
          "editorMode": "code",
          "expr": "quantile(0.95, probe_success{job=\"blackbox-icmp-vpn\",instance=~\"192.168.200.2\",location=\"pt\"}[5m])",
          "legendFormat": "EZ",
          "range": true,
          "refId": "A"
        },
        {
          "datasource": {
            "type": "prometheus",
            "uid": "${datasource}"
          },
          "editorMode": "code",
          "expr": "quantile(0.95, probe_success{job=\"blackbox-icmp-vpn\",instance=~\"192.168.200.3\",location=\"pt\"}[5m])",
          "hide": false,
          "legendFormat": "DD",
          "range": true,
          "refId": "B"
        },
        {
          "datasource": {
            "type": "prometheus",
            "uid": "${datasource}"
          },
          "editorMode": "code",
          "expr": "quantile(0.95, probe_success{job=\"blackbox-icmp-vpn\",instance=~\"192.168.200.1\",location=\"pt\"}[5m])",
          "hide": false,
          "legendFormat": "RS",
          "range": true,
          "refId": "C"
        },
        {
          "datasource": {
            "type": "prometheus",
            "uid": "${datasource}"
          },
          "editorMode": "code",
          "expr": "quantile(0.95, probe_success{job=\"blackbox-icmp-vpn\",instance=~\"192.168.200.5\",location=\"pt\"}[5m])",
          "hide": false,
          "legendFormat": "SW",
          "range": true,
          "refId": "D"
        }
      ],
      "title": "VPN Health PT",
      "type": "stat"
    },
    {
      "datasource": {
        "type": "prometheus",
        "uid": "${datasource}"
      },
      "fieldConfig": {
        "defaults": {
          "color": {
            "mode": "thresholds"
          },
          "mappings": [],
          "thresholds": {
            "mode": "absolute",
            "steps": [
              {
                "color": "green",
                "value": null
              },
              {
                "color": "#EAB839",
                "value": 0.1
              },
              {
                "color": "red",
                "value": 0.2
              }
            ]
          },
          "unit": "s"
        },
        "overrides": []
      },
      "gridPos": {
        "h": 4,
        "w": 4,
        "x": 12,
        "y": 1
      },
      "id": 55,
      "options": {
        "colorMode": "background",
        "graphMode": "area",
        "justifyMode": "auto",
        "orientation": "auto",
        "reduceOptions": {
          "calcs": [
            "last"
          ],
          "fields": "",
          "values": false
        },
        "textMode": "auto"
      },
      "pluginVersion": "9.3.6",
      "targets": [
        {
          "datasource": {
            "type": "prometheus",
            "uid": "${datasource}"
          },
          "editorMode": "code",
          "expr": "avg(quantile_over_time(0.95, probe_icmp_duration_seconds{instance=\"192.168.200.3\",job=\"blackbox-icmp-vpn\",location=\"ez\"} > 0.01)[1h])",
          "hide": false,
          "legendFormat": "DD",
          "range": true,
          "refId": "B"
        },
        {
          "datasource": {
            "type": "prometheus",
            "uid": "${datasource}"
          },
          "editorMode": "code",
          "expr": "avg(quantile_over_time(0.95, probe_icmp_duration_seconds{instance=\"192.168.200.4\",job=\"blackbox-icmp-vpn\",location=\"ez\"} > 0.01)[1h])",
          "hide": false,
          "legendFormat": "PT",
          "range": true,
          "refId": "A"
        },
        {
          "datasource": {
            "type": "prometheus",
            "uid": "${datasource}"
          },
          "editorMode": "code",
          "expr": "avg(quantile_over_time(0.95, probe_icmp_duration_seconds{instance=\"192.168.200.1\",job=\"blackbox-icmp-vpn\",location=\"ez\"} > 0.01)[1h])",
          "hide": false,
          "legendFormat": "RS",
          "range": true,
          "refId": "C"
        },
        {
          "datasource": {
            "type": "prometheus",
            "uid": "${datasource}"
          },
          "editorMode": "code",
          "expr": "avg(quantile_over_time(0.95, probe_icmp_duration_seconds{instance=\"192.168.200.5\",job=\"blackbox-icmp-vpn\",location=\"ez\"} > 0.01)[1h])",
          "hide": false,
          "legendFormat": "SW",
          "range": true,
          "refId": "D"
        }
      ],
      "title": "VPN Latency EZ",
      "type": "stat"
    },
    {
      "datasource": {
        "type": "prometheus",
        "uid": "${datasource}"
      },
      "fieldConfig": {
        "defaults": {
          "color": {
            "mode": "thresholds"
          },
          "mappings": [],
          "thresholds": {
            "mode": "absolute",
            "steps": [
              {
                "color": "green",
                "value": null
              },
              {
                "color": "#EAB839",
                "value": 0.1
              },
              {
                "color": "red",
                "value": 0.2
              }
            ]
          },
          "unit": "s"
        },
        "overrides": []
      },
      "gridPos": {
        "h": 4,
        "w": 4,
        "x": 16,
        "y": 1
      },
      "id": 54,
      "options": {
        "colorMode": "background",
        "graphMode": "area",
        "justifyMode": "auto",
        "orientation": "auto",
        "reduceOptions": {
          "calcs": [
            "last"
          ],
          "fields": "",
          "values": false
        },
        "textMode": "auto"
      },
      "pluginVersion": "9.3.6",
      "targets": [
        {
          "datasource": {
            "type": "prometheus",
            "uid": "${datasource}"
          },
          "editorMode": "code",
          "expr": "avg(quantile_over_time(0.95, probe_icmp_duration_seconds{instance=\"192.168.200.2\",job=\"blackbox-icmp-vpn\",location=\"dd\"} > 0.01)[1h])",
          "hide": false,
          "legendFormat": "EZ",
          "range": true,
          "refId": "B"
        },
        {
          "datasource": {
            "type": "prometheus",
            "uid": "${datasource}"
          },
          "editorMode": "code",
          "expr": "avg(quantile_over_time(0.95, probe_icmp_duration_seconds{instance=\"192.168.200.4\",job=\"blackbox-icmp-vpn\",location=\"dd\"} > 0.01)[1h])",
          "hide": false,
          "legendFormat": "PT",
          "range": true,
          "refId": "A"
        },
        {
          "datasource": {
            "type": "prometheus",
            "uid": "${datasource}"
          },
          "editorMode": "code",
          "expr": "avg(quantile_over_time(0.95, probe_icmp_duration_seconds{instance=\"192.168.200.1\",job=\"blackbox-icmp-vpn\",location=\"dd\"} > 0.01)[1h])",
          "hide": false,
          "legendFormat": "RS",
          "range": true,
          "refId": "C"
        },
        {
          "datasource": {
            "type": "prometheus",
            "uid": "${datasource}"
          },
          "editorMode": "code",
          "expr": "avg(quantile_over_time(0.95, probe_icmp_duration_seconds{instance=\"192.168.200.5\",job=\"blackbox-icmp-vpn\",location=\"dd\"} > 0.01)[1h])",
          "hide": false,
          "legendFormat": "SW",
          "range": true,
          "refId": "D"
        }
      ],
      "title": "VPN Latency DD",
      "type": "stat"
    },
    {
      "datasource": {
        "type": "prometheus",
        "uid": "${datasource}"
      },
      "fieldConfig": {
        "defaults": {
          "color": {
            "mode": "thresholds"
          },
          "mappings": [],
          "thresholds": {
            "mode": "absolute",
            "steps": [
              {
                "color": "green",
                "value": null
              },
              {
                "color": "#EAB839",
                "value": 0.1
              },
              {
                "color": "red",
                "value": 0.2
              }
            ]
          },
          "unit": "s"
        },
        "overrides": []
      },
      "gridPos": {
        "h": 4,
        "w": 4,
        "x": 20,
        "y": 1
      },
      "id": 56,
      "options": {
        "colorMode": "background",
        "graphMode": "area",
        "justifyMode": "auto",
        "orientation": "auto",
        "reduceOptions": {
          "calcs": [
            "last"
          ],
          "fields": "",
          "values": false
        },
        "textMode": "auto"
      },
      "pluginVersion": "9.3.6",
      "targets": [
        {
          "datasource": {
            "type": "prometheus",
            "uid": "${datasource}"
          },
          "editorMode": "code",
          "expr": "avg(quantile_over_time(0.95, probe_icmp_duration_seconds{instance=\"192.168.200.2\",job=\"blackbox-icmp-vpn\",location=\"pt\"} > 0.01)[1h])",
          "hide": false,
          "legendFormat": "EZ",
          "range": true,
          "refId": "B"
        },
        {
          "datasource": {
            "type": "prometheus",
            "uid": "${datasource}"
          },
          "editorMode": "code",
          "expr": "avg(quantile_over_time(0.95, probe_icmp_duration_seconds{instance=\"192.168.200.3\",job=\"blackbox-icmp-vpn\",location=\"pt\"} > 0.01)[1h])",
          "hide": false,
          "legendFormat": "DD",
          "range": true,
          "refId": "A"
        },
        {
          "datasource": {
            "type": "prometheus",
            "uid": "${datasource}"
          },
          "editorMode": "code",
          "expr": "avg(quantile_over_time(0.95, probe_icmp_duration_seconds{instance=\"192.168.200.1\",job=\"blackbox-icmp-vpn\",location=\"pt\"} > 0.01)[1h])",
          "hide": false,
          "legendFormat": "RS",
          "range": true,
          "refId": "C"
        },
        {
          "datasource": {
            "type": "prometheus",
            "uid": "${datasource}"
          },
          "editorMode": "code",
          "expr": "avg(quantile_over_time(0.95, probe_icmp_duration_seconds{instance=\"192.168.200.5\",job=\"blackbox-icmp-vpn\",location=\"pt\"} > 0.01)[1h])",
          "hide": false,
          "legendFormat": "SW",
          "range": true,
          "refId": "D"
        }
      ],
      "title": "VPN Latency PT",
      "type": "stat"
    },
    {
      "datasource": {
        "type": "prometheus",
        "uid": "${datasource}"
      },
      "fieldConfig": {
        "defaults": {
          "color": {
            "mode": "thresholds"
          },
          "mappings": [],
          "thresholds": {
            "mode": "absolute",
            "steps": [
              {
                "color": "green",
                "value": null
              },
              {
                "color": "red",
                "value": 1
              }
            ]
          }
        },
        "overrides": []
      },
      "gridPos": {
        "h": 4,
        "w": 2,
        "x": 0,
        "y": 5
      },
      "id": 48,
      "options": {
        "colorMode": "background",
        "graphMode": "area",
        "justifyMode": "auto",
        "orientation": "auto",
        "reduceOptions": {
          "calcs": [
            "last"
          ],
          "fields": "",
          "values": false
        },
        "textMode": "auto"
      },
      "pluginVersion": "9.3.6",
      "targets": [
        {
          "datasource": {
            "type": "prometheus",
            "uid": "${datasource}"
          },
          "editorMode": "code",
          "expr": "max(increase(node_network_transmit_errs_total{instance=~\"^router.*\"}[5m] or node_network_receive_errs_total{instance=~\"^router.*\"}[5m]) > 0) or vector(0)",
          "legendFormat": "__auto",
          "range": true,
          "refId": "A"
        }
      ],
      "title": "Network Errors",
      "type": "stat"
    },
    {
      "datasource": {
        "type": "prometheus",
        "uid": "${datasource}"
      },
      "fieldConfig": {
        "defaults": {
          "color": {
            "mode": "thresholds"
          },
          "mappings": [],
          "thresholds": {
            "mode": "absolute",
            "steps": [
              {
                "color": "green",
                "value": null
              },
              {
                "color": "#EAB839",
                "value": 0.3
              },
              {
                "color": "red",
                "value": 0.7
              }
            ]
          },
          "unit": "s"
        },
        "overrides": []
      },
      "gridPos": {
        "h": 4,
        "w": 4,
        "x": 2,
        "y": 5
      },
      "id": 17,
      "options": {
        "colorMode": "background",
        "graphMode": "area",
        "justifyMode": "auto",
        "orientation": "auto",
        "reduceOptions": {
          "calcs": [
            "last"
          ],
          "fields": "",
          "values": false
        },
        "textMode": "auto"
      },
      "pluginVersion": "9.3.6",
      "targets": [
        {
          "datasource": {
            "type": "prometheus",
            "uid": "${datasource}"
          },
          "editorMode": "code",
          "exemplar": false,
          "expr": "quantile(0.95, probe_icmp_duration_seconds{job=\"blackbox-icmp-internet\"}[1h]) by (location)",
          "instant": false,
          "legendFormat": "__auto",
          "range": true,
          "refId": "A"
        }
      ],
      "title": "Uplink Latency 1h",
      "type": "stat"
    },
    {
      "datasource": {
        "type": "prometheus",
        "uid": "${datasource}"
      },
      "fieldConfig": {
        "defaults": {
          "color": {
            "mode": "thresholds"
          },
          "mappings": [],
          "thresholds": {
            "mode": "absolute",
            "steps": [
              {
                "color": "red",
                "value": null
              },
              {
                "color": "green",
                "value": 614400
              }
            ]
          },
          "unit": "bytes"
        },
        "overrides": []
      },
      "gridPos": {
        "h": 4,
        "w": 4,
        "x": 6,
        "y": 5
      },
      "id": 33,
      "options": {
        "colorMode": "background",
        "graphMode": "area",
        "justifyMode": "auto",
        "orientation": "auto",
        "reduceOptions": {
          "calcs": [
            "last"
          ],
          "fields": "",
          "values": false
        },
        "textMode": "auto"
      },
      "pluginVersion": "9.3.6",
      "targets": [
        {
          "datasource": {
            "type": "prometheus",
            "uid": "${datasource}"
          },
          "editorMode": "code",
          "expr": "max(increase(node_network_transmit_bytes_total{job=\"routers\",device=~\"igc0|em1\"}[4h])) by (location) - max(increase(node_network_transmit_bytes_total{job=\"routers\",device=\"wg0\"}[4h])) by (location)",
          "legendFormat": "{{location}}",
          "range": true,
          "refId": "A"
        }
      ],
      "title": "Uplink Data w/o VPN 4h",
      "type": "stat"
    },
    {
      "datasource": {
        "type": "prometheus",
        "uid": "${datasource}"
      },
      "fieldConfig": {
        "defaults": {
          "color": {
            "mode": "thresholds"
          },
          "mappings": [],
          "thresholds": {
            "mode": "absolute",
            "steps": [
              {
                "color": "red",
                "value": null
              },
              {
                "color": "green",
                "value": 614400
              }
            ]
          },
          "unit": "bytes"
        },
        "overrides": []
      },
      "gridPos": {
        "h": 4,
        "w": 7,
        "x": 10,
        "y": 5
      },
      "id": 32,
      "options": {
        "colorMode": "background",
        "graphMode": "area",
        "justifyMode": "auto",
        "orientation": "auto",
        "reduceOptions": {
          "calcs": [
            "last"
          ],
          "fields": "",
          "values": false
        },
        "textMode": "auto"
      },
      "pluginVersion": "9.3.6",
      "targets": [
        {
          "datasource": {
            "type": "prometheus",
            "uid": "${datasource}"
          },
          "editorMode": "code",
          "expr": "max by (instance) (increase(node_network_transmit_bytes_total{job=~\"routers|enclave\",device=\"wg0\"}[4h]))",
          "hide": false,
          "legendFormat": "{{location}}",
          "range": true,
          "refId": "B"
        }
      ],
      "title": "VPN Data Sent",
      "type": "stat"
    },
    {
      "datasource": {
        "type": "prometheus",
        "uid": "${datasource}"
      },
      "fieldConfig": {
        "defaults": {
          "color": {
            "mode": "thresholds"
          },
          "mappings": [],
          "thresholds": {
            "mode": "absolute",
            "steps": [
              {
                "color": "red",
                "value": null
              },
              {
                "color": "green",
                "value": 614400
              }
            ]
          },
          "unit": "bytes"
        },
        "overrides": []
      },
      "gridPos": {
        "h": 4,
        "w": 7,
        "x": 17,
        "y": 5
      },
      "id": 63,
      "options": {
        "colorMode": "background",
        "graphMode": "area",
        "justifyMode": "auto",
        "orientation": "auto",
        "reduceOptions": {
          "calcs": [
            "last"
          ],
          "fields": "",
          "values": false
        },
        "textMode": "auto"
      },
      "pluginVersion": "9.3.6",
      "targets": [
        {
          "datasource": {
            "type": "prometheus",
            "uid": "${datasource}"
          },
          "editorMode": "code",
          "expr": "max by (instance) (increase(node_network_receive_bytes_total{job=~\"routers|enclave\",device=\"wg0\"}[4h]))",
          "hide": false,
          "legendFormat": "{{location}}",
          "range": true,
          "refId": "B"
        }
      ],
      "title": "VPN Data Receive",
      "type": "stat"
    },
    {
      "collapsed": false,
      "gridPos": {
        "h": 1,
        "w": 24,
        "x": 0,
        "y": 9
      },
      "id": 16,
      "panels": [],
      "title": "Critical Infrastructure",
      "type": "row"
    },
    {
      "datasource": {
        "type": "prometheus",
        "uid": "${datasource}"
      },
      "fieldConfig": {
        "defaults": {
          "color": {
            "mode": "thresholds"
          },
          "mappings": [],
          "max": 1,
          "min": 0,
          "thresholds": {
            "mode": "absolute",
            "steps": [
              {
                "color": "red",
                "value": null
              },
              {
                "color": "yellow",
                "value": 2
              },
              {
                "color": "green",
                "value": 3
              }
            ]
          }
        },
        "overrides": []
      },
      "gridPos": {
        "h": 4,
        "w": 2,
        "x": 0,
        "y": 10
      },
      "id": 24,
      "options": {
        "colorMode": "background",
        "graphMode": "area",
        "justifyMode": "auto",
        "orientation": "auto",
        "reduceOptions": {
          "calcs": [
            "last"
          ],
          "fields": "",
          "values": false
        },
        "textMode": "auto"
      },
      "pluginVersion": "9.3.6",
      "targets": [
        {
          "datasource": {
            "type": "prometheus",
            "uid": "${datasource}"
          },
          "editorMode": "code",
          "expr": "count(up{job=\"vault-prd-api\"} == 1)",
          "legendFormat": "{{location}}",
          "range": true,
          "refId": "A"
        }
      ],
      "title": "# Vault Nodes",
      "type": "stat"
    },
    {
      "datasource": {
        "type": "prometheus",
        "uid": "${datasource}"
      },
      "fieldConfig": {
        "defaults": {
          "color": {
            "mode": "thresholds"
          },
          "mappings": [],
          "max": 3,
          "min": 0,
          "thresholds": {
            "mode": "absolute",
            "steps": [
              {
                "color": "red",
                "value": null
              },
              {
                "color": "yellow",
                "value": 2
              },
              {
                "color": "green",
                "value": 3
              }
            ]
          }
        },
        "overrides": []
      },
      "gridPos": {
        "h": 4,
        "w": 2,
        "x": 2,
        "y": 10
      },
      "id": 18,
      "options": {
        "colorMode": "background",
        "graphMode": "area",
        "justifyMode": "auto",
        "orientation": "auto",
        "reduceOptions": {
          "calcs": [
            "last"
          ],
          "fields": "",
          "values": false
        },
        "textMode": "auto"
      },
      "pluginVersion": "9.3.6",
      "targets": [
        {
          "datasource": {
            "type": "prometheus",
            "uid": "${datasource}"
          },
          "editorMode": "code",
          "expr": "count(vault_core_unsealed == 1)",
          "legendFormat": "{{location}}",
          "range": true,
          "refId": "A"
        }
      ],
      "title": "Unsealed Vault Nodes",
      "type": "stat"
    },
    {
      "datasource": {
        "type": "prometheus",
        "uid": "${datasource}"
      },
      "fieldConfig": {
        "defaults": {
          "color": {
            "mode": "thresholds"
          },
          "mappings": [],
          "max": 3,
          "min": 0,
          "thresholds": {
            "mode": "absolute",
            "steps": [
              {
                "color": "red",
                "value": null
              },
              {
                "color": "#EAB839",
                "value": 2
              },
              {
                "color": "green",
                "value": 3
              }
            ]
          }
        },
        "overrides": []
      },
      "gridPos": {
        "h": 4,
        "w": 2,
        "x": 4,
        "y": 10
      },
      "id": 8,
      "options": {
        "colorMode": "background",
        "graphMode": "area",
        "justifyMode": "auto",
        "orientation": "auto",
        "reduceOptions": {
          "calcs": [
            "last"
          ],
          "fields": "",
          "values": false
        },
        "textMode": "auto"
      },
      "pluginVersion": "9.3.6",
      "targets": [
        {
          "datasource": {
            "type": "prometheus",
            "uid": "${datasource}"
          },
          "editorMode": "code",
          "expr": "count(max by (instance) (vault_autopilot_node_healthy) == 1) or vector(0)",
          "legendFormat": "__auto",
          "range": true,
          "refId": "A"
        }
      ],
      "title": "Vault Unhealthy Nodes",
      "type": "stat"
    },
    {
      "datasource": {
        "type": "prometheus",
        "uid": "${datasource}"
      },
      "fieldConfig": {
        "defaults": {
          "color": {
            "mode": "thresholds"
          },
          "decimals": 0,
          "mappings": [],
          "max": 7776000,
          "min": 0,
          "thresholds": {
            "mode": "absolute",
            "steps": [
              {
                "color": "red",
                "value": null
              },
              {
                "color": "#EAB839",
                "value": 2160000
              },
              {
                "color": "green",
                "value": 2592000
              }
            ]
          },
          "unit": "s"
        },
        "overrides": []
      },
      "gridPos": {
        "h": 4,
        "w": 1,
        "x": 6,
        "y": 10
      },
      "id": 2,
      "options": {
        "colorMode": "background",
        "graphMode": "area",
        "justifyMode": "auto",
        "orientation": "auto",
        "reduceOptions": {
          "calcs": [
            "last"
          ],
          "fields": "",
          "values": false
        },
        "textMode": "auto"
      },
      "pluginVersion": "9.3.6",
      "targets": [
        {
          "datasource": {
            "type": "prometheus",
            "uid": "${datasource}"
          },
          "editorMode": "code",
          "exemplar": false,
          "expr": "min(probe_ssl_earliest_cert_expiry, acmevault_server_certificate_expiry_time) - time()",
          "instant": true,
          "legendFormat": "__auto",
          "range": false,
          "refId": "A"
        }
      ],
      "title": "x509",
      "type": "stat"
    },
    {
      "datasource": {
        "type": "prometheus",
        "uid": "${datasource}"
      },
      "fieldConfig": {
        "defaults": {
          "color": {
            "mode": "thresholds"
          },
          "decimals": 0,
          "mappings": [],
          "max": 300,
          "min": 0,
          "thresholds": {
            "mode": "absolute",
            "steps": [
              {
                "color": "green",
                "value": null
              },
              {
                "color": "#EAB839",
                "value": 180
              },
              {
                "color": "red",
                "value": 300
              }
            ]
          },
          "unit": "s"
        },
        "overrides": []
      },
      "gridPos": {
        "h": 4,
        "w": 3,
        "x": 7,
        "y": 10
      },
      "id": 46,
      "options": {
        "colorMode": "background",
        "graphMode": "area",
        "justifyMode": "auto",
        "orientation": "auto",
        "reduceOptions": {
          "calcs": [
            "last"
          ],
          "fields": "",
          "values": false
        },
        "textMode": "auto"
      },
      "pluginVersion": "9.3.6",
      "targets": [
        {
          "datasource": {
            "type": "prometheus",
            "uid": "${datasource}"
          },
          "editorMode": "code",
          "expr": "time() - max(dyndns_client_ip_resolves_last_check_timestamp_seconds) by (host)",
          "legendFormat": "__auto",
          "range": true,
          "refId": "A"
        }
      ],
      "title": "Dyndns Client Checks",
      "type": "stat"
    },
    {
      "datasource": {
        "type": "prometheus",
        "uid": "${datasource}"
      },
      "fieldConfig": {
        "defaults": {
          "color": {
            "mode": "thresholds"
          },
          "decimals": 0,
          "mappings": [],
          "max": 3,
          "min": 0,
          "thresholds": {
            "mode": "absolute",
            "steps": [
              {
                "color": "red",
                "value": null
              },
              {
                "color": "green",
                "value": 3
              }
            ]
          },
          "unit": "none"
        },
        "overrides": []
      },
      "gridPos": {
        "h": 4,
        "w": 2,
        "x": 10,
        "y": 10
      },
      "id": 60,
      "options": {
        "colorMode": "background",
        "graphMode": "area",
        "justifyMode": "auto",
        "orientation": "auto",
        "reduceOptions": {
          "calcs": [
            "last"
          ],
          "fields": "",
          "values": false
        },
        "textMode": "auto"
      },
      "pluginVersion": "9.3.6",
      "targets": [
        {
          "datasource": {
            "type": "prometheus",
            "uid": "${datasource}"
          },
          "editorMode": "code",
          "expr": "count(dyndns_client_current_state_bool{state=\"ipConfirmedState\"} == 1)",
          "legendFormat": "__auto",
          "range": true,
          "refId": "A"
        }
      ],
      "title": "IpConfirmedState",
      "type": "stat"
    },
    {
      "datasource": {
        "type": "prometheus",
        "uid": "${datasource}"
      },
      "fieldConfig": {
        "defaults": {
          "color": {
            "mode": "thresholds"
          },
          "mappings": [],
          "max": 3,
          "min": 0,
          "thresholds": {
            "mode": "absolute",
            "steps": [
              {
                "color": "red",
                "value": null
              },
              {
                "color": "#EAB839",
                "value": 2
              },
              {
                "color": "green",
                "value": 3
              }
            ]
          }
        },
        "overrides": []
      },
      "gridPos": {
        "h": 4,
        "w": 2,
        "x": 12,
        "y": 10
      },
      "id": 26,
      "options": {
        "colorMode": "background",
        "graphMode": "area",
        "justifyMode": "auto",
        "orientation": "auto",
        "reduceOptions": {
          "calcs": [
            "lastNotNull"
          ],
          "fields": "",
          "values": false
        },
        "textMode": "auto"
      },
      "pluginVersion": "9.3.6",
      "targets": [
        {
          "datasource": {
            "type": "prometheus",
            "uid": "${datasource}"
          },
          "editorMode": "code",
          "expr": "count(min(up{job=\"prometheus-cluster\"} == 1) by (location))",
          "legendFormat": "__auto",
          "range": true,
          "refId": "A"
        }
      ],
      "title": "#Prom Inst.",
      "type": "stat"
    },
    {
      "datasource": {
        "type": "prometheus",
        "uid": "${datasource}"
      },
      "fieldConfig": {
        "defaults": {
          "color": {
            "mode": "thresholds"
          },
          "mappings": [],
          "max": 3,
          "min": 0,
          "thresholds": {
            "mode": "absolute",
            "steps": [
              {
                "color": "red",
                "value": null
              },
              {
                "color": "#EAB839",
                "value": 2
              },
              {
                "color": "green",
                "value": 3
              }
            ]
          }
        },
        "overrides": []
      },
      "gridPos": {
        "h": 4,
        "w": 2,
        "x": 14,
        "y": 10
      },
      "id": 30,
      "options": {
        "colorMode": "background",
        "graphMode": "area",
        "justifyMode": "auto",
        "orientation": "auto",
        "reduceOptions": {
          "calcs": [
            "last"
          ],
          "fields": "",
          "values": false
        },
        "textMode": "auto"
      },
      "pluginVersion": "9.3.6",
      "targets": [
        {
          "datasource": {
            "type": "prometheus",
            "uid": "${datasource}"
          },
          "editorMode": "code",
          "expr": "count(min(up{job=\"alertmanager-cluster\"} == 1) by (location))",
          "legendFormat": "__auto",
          "range": true,
          "refId": "A"
        }
      ],
      "title": "# Alertmanager",
      "type": "stat"
    },
    {
      "datasource": {
        "type": "prometheus",
        "uid": "${datasource}"
      },
      "fieldConfig": {
        "defaults": {
          "color": {
            "mode": "thresholds"
          },
          "mappings": [],
          "thresholds": {
            "mode": "absolute",
            "steps": [
              {
                "color": "green",
                "value": null
              },
              {
                "color": "red",
                "value": 1
              }
            ]
          }
        },
        "overrides": []
      },
      "gridPos": {
        "h": 4,
        "w": 2,
        "x": 16,
        "y": 10
      },
      "id": 31,
      "options": {
        "colorMode": "background",
        "graphMode": "area",
        "justifyMode": "auto",
        "orientation": "auto",
        "reduceOptions": {
          "calcs": [
            "last"
          ],
          "fields": "",
          "values": false
        },
        "textMode": "auto"
      },
      "pluginVersion": "9.3.6",
      "targets": [
        {
          "datasource": {
            "type": "prometheus",
            "uid": "${datasource}"
          },
          "editorMode": "code",
          "expr": "sum(vmalert_alerting_rules_error)",
          "legendFormat": "__auto",
          "range": true,
          "refId": "A"
        }
      ],
      "title": "Alert Rules Errors",
      "type": "stat"
    },
    {
      "datasource": {
        "type": "prometheus",
        "uid": "${datasource}"
      },
      "fieldConfig": {
        "defaults": {
          "color": {
            "mode": "thresholds"
          },
          "mappings": [],
          "thresholds": {
            "mode": "absolute",
            "steps": [
              {
                "color": "green",
                "value": null
              },
              {
                "color": "red",
                "value": 1
              }
            ]
          }
        },
        "overrides": []
      },
      "gridPos": {
        "h": 4,
        "w": 2,
        "x": 18,
        "y": 10
      },
      "id": 35,
      "options": {
        "colorMode": "background",
        "graphMode": "area",
        "justifyMode": "auto",
        "orientation": "auto",
        "reduceOptions": {
          "calcs": [
            "last"
          ],
          "fields": "",
          "values": false
        },
        "textMode": "auto"
      },
      "pluginVersion": "9.3.6",
      "targets": [
        {
          "datasource": {
            "type": "prometheus",
            "uid": "${datasource}"
          },
          "editorMode": "code",
          "expr": "sum(increase(alertmanager_notifications_failed_total[15m]))",
          "legendFormat": "__auto",
          "range": true,
          "refId": "A"
        }
      ],
      "title": "Alertmanager Failed Notifications",
      "type": "stat"
    },
    {
      "datasource": {
        "type": "prometheus",
        "uid": "${datasource}"
      },
      "fieldConfig": {
        "defaults": {
          "color": {
            "mode": "thresholds"
          },
          "mappings": [],
          "thresholds": {
            "mode": "absolute",
            "steps": [
              {
                "color": "green",
                "value": null
              },
              {
                "color": "red",
                "value": 1
              }
            ]
          }
        },
        "overrides": []
      },
      "gridPos": {
        "h": 4,
        "w": 2,
        "x": 20,
        "y": 10
      },
      "id": 42,
      "options": {
        "colorMode": "background",
        "graphMode": "area",
        "justifyMode": "auto",
        "orientation": "auto",
        "reduceOptions": {
          "calcs": [
            "last"
          ],
          "fields": "",
          "values": false
        },
        "textMode": "auto"
      },
      "pluginVersion": "9.3.6",
      "targets": [
        {
          "datasource": {
            "type": "prometheus",
            "uid": "${datasource}"
          },
          "editorMode": "code",
          "expr": "count(count by (alertname) (vmalert_alerts_firing{alertname!=\"Dead Man's Switch\"} > 0 or ALERTS > 0)) or vector(0)",
          "legendFormat": "__auto",
          "range": true,
          "refId": "A"
        }
      ],
      "title": "Firing Alerts",
      "type": "stat"
    },
    {
      "datasource": {
        "type": "prometheus",
        "uid": "${datasource}"
      },
      "fieldConfig": {
        "defaults": {
          "color": {
            "mode": "thresholds"
          },
          "mappings": [],
          "thresholds": {
            "mode": "absolute",
            "steps": [
              {
                "color": "green",
                "value": null
              },
              {
                "color": "orange",
                "value": 1
              }
            ]
          }
        },
        "overrides": []
      },
      "gridPos": {
        "h": 4,
        "w": 2,
        "x": 22,
        "y": 10
      },
      "id": 43,
      "options": {
        "colorMode": "background",
        "graphMode": "area",
        "justifyMode": "auto",
        "orientation": "auto",
        "reduceOptions": {
          "calcs": [
            "lastNotNull"
          ],
          "fields": "",
          "values": false
        },
        "textMode": "auto"
      },
      "pluginVersion": "9.3.6",
      "targets": [
        {
          "datasource": {
            "type": "prometheus",
            "uid": "${datasource}"
          },
          "editorMode": "code",
          "expr": "count(count by (alertname) (vmalert_alerts_pending > 0)) or vector(0)",
          "legendFormat": "__auto",
          "range": true,
          "refId": "A"
        }
      ],
      "title": "Pending Alerts",
      "type": "stat"
    },
    {
      "datasource": {
        "type": "prometheus",
        "uid": "${datasource}"
      },
      "fieldConfig": {
        "defaults": {
          "color": {
            "mode": "palette-classic"
          },
          "custom": {
            "axisCenteredZero": false,
            "axisColorMode": "text",
            "axisLabel": "",
            "axisPlacement": "auto",
            "barAlignment": 0,
            "drawStyle": "line",
            "fillOpacity": 30,
            "gradientMode": "none",
            "hideFrom": {
              "legend": false,
              "tooltip": false,
              "viz": false
            },
            "lineInterpolation": "linear",
            "lineWidth": 1,
            "pointSize": 5,
            "scaleDistribution": {
              "type": "linear"
            },
            "showPoints": "auto",
            "spanNulls": false,
            "stacking": {
              "group": "A",
              "mode": "normal"
            },
            "thresholdsStyle": {
              "mode": "off"
            }
          },
          "mappings": [],
          "thresholds": {
            "mode": "absolute",
            "steps": [
              {
                "color": "green",
                "value": null
              },
              {
                "color": "red",
                "value": 80
              }
            ]
          }
        },
        "overrides": []
      },
      "gridPos": {
        "h": 8,
        "w": 12,
        "x": 0,
        "y": 14
      },
      "id": 41,
      "options": {
        "legend": {
          "calcs": [],
          "displayMode": "list",
          "placement": "right",
          "showLegend": true
        },
        "tooltip": {
          "mode": "single",
          "sort": "none"
        }
      },
      "pluginVersion": "9.3.2",
      "targets": [
        {
          "datasource": {
            "type": "prometheus",
            "uid": "${datasource}"
          },
          "editorMode": "code",
          "exemplar": false,
          "expr": "sort_desc(sum((vmalert_alerts_firing{alertname!=\"Dead Man's Switch\"} > 0 / 3) or ALERTS{alertstate=\"firing\"} > 0) by (alertname))",
          "format": "time_series",
          "instant": false,
          "legendFormat": "__auto",
          "range": true,
          "refId": "A"
        }
      ],
      "title": "Active Alerts",
      "transformations": [],
      "type": "timeseries"
    },
    {
      "datasource": {
        "type": "prometheus",
        "uid": "${datasource}"
      },
      "fieldConfig": {
        "defaults": {
          "color": {
            "mode": "palette-classic"
          },
          "custom": {
            "axisCenteredZero": false,
            "axisColorMode": "text",
            "axisLabel": "",
            "axisPlacement": "auto",
            "barAlignment": 0,
            "drawStyle": "line",
            "fillOpacity": 30,
            "gradientMode": "none",
            "hideFrom": {
              "legend": false,
              "tooltip": false,
              "viz": false
            },
            "lineInterpolation": "linear",
            "lineWidth": 1,
            "pointSize": 5,
            "scaleDistribution": {
              "type": "linear"
            },
            "showPoints": "auto",
            "spanNulls": false,
            "stacking": {
              "group": "A",
              "mode": "normal"
            },
            "thresholdsStyle": {
              "mode": "off"
            }
          },
          "mappings": [],
          "thresholds": {
            "mode": "absolute",
            "steps": [
              {
                "color": "green",
                "value": null
              },
              {
                "color": "red",
                "value": 80
              }
            ]
          }
        },
        "overrides": []
      },
      "gridPos": {
        "h": 8,
        "w": 12,
        "x": 12,
        "y": 14
      },
      "id": 67,
      "options": {
        "legend": {
          "calcs": [],
          "displayMode": "list",
          "placement": "right",
          "showLegend": true
        },
        "tooltip": {
          "mode": "single",
          "sort": "none"
        }
      },
      "pluginVersion": "9.3.2",
      "targets": [
        {
          "datasource": {
            "type": "prometheus",
            "uid": "${datasource}"
          },
          "editorMode": "code",
          "exemplar": false,
          "expr": "sort_desc(sum((vmalert_alerts_pending{alertname!=\"Dead Man's Switch\"} > 0 / 3) or ALERTS{alertstate=\"pending\"} > 0) by (alertname))",
          "format": "time_series",
          "instant": false,
          "legendFormat": "__auto",
          "range": true,
          "refId": "A"
        }
      ],
      "title": "Pending Alerts",
      "transformations": [],
      "type": "timeseries"
    },
    {
      "collapsed": false,
      "gridPos": {
        "h": 1,
        "w": 24,
        "x": 0,
        "y": 22
      },
      "id": 23,
      "panels": [],
      "title": "Ambience",
      "type": "row"
    },
    {
      "datasource": {
        "type": "prometheus",
        "uid": "${datasource}"
      },
      "fieldConfig": {
        "defaults": {
          "color": {
            "mode": "thresholds"
          },
          "mappings": [],
          "max": 30,
          "min": 13,
          "thresholds": {
            "mode": "absolute",
            "steps": [
              {
                "color": "super-light-blue",
                "value": null
              },
              {
                "color": "blue",
                "value": 16
              },
              {
                "color": "green",
                "value": 20
              },
              {
                "color": "red",
                "value": 26
              },
              {
                "color": "dark-red",
                "value": 32
              }
            ]
          },
          "unit": "celsius"
        },
        "overrides": []
      },
      "gridPos": {
        "h": 4,
        "w": 4,
        "x": 0,
        "y": 23
      },
      "id": 20,
      "options": {
        "colorMode": "background",
        "graphMode": "area",
        "justifyMode": "auto",
        "orientation": "auto",
        "reduceOptions": {
          "calcs": [
            "last"
          ],
          "fields": "",
          "values": false
        },
        "textMode": "auto"
      },
      "pluginVersion": "9.3.6",
      "targets": [
        {
          "datasource": {
            "type": "prometheus",
            "uid": "${datasource}"
          },
          "editorMode": "code",
          "expr": "avg_over_time(gobot_bme280_sensor_temperature_celsius{location=\"dd\"}[1h])",
          "legendFormat": "{{placement}}",
          "range": true,
          "refId": "A"
        }
      ],
      "title": "Temperature DD",
      "type": "stat"
    },
    {
      "datasource": {
        "type": "prometheus",
        "uid": "${datasource}"
      },
      "fieldConfig": {
        "defaults": {
          "color": {
            "mode": "thresholds"
          },
          "mappings": [],
          "max": 80,
          "min": 20,
          "thresholds": {
            "mode": "absolute",
            "steps": [
              {
                "color": "red",
                "value": null
              },
              {
                "color": "green",
                "value": 25
              },
              {
                "color": "red",
                "value": 75
              }
            ]
          },
          "unit": "humidity"
        },
        "overrides": []
      },
      "gridPos": {
        "h": 4,
        "w": 4,
        "x": 4,
        "y": 23
      },
      "id": 21,
      "options": {
        "colorMode": "background",
        "graphMode": "area",
        "justifyMode": "auto",
        "orientation": "auto",
        "reduceOptions": {
          "calcs": [
            "last"
          ],
          "fields": "",
          "values": false
        },
        "textMode": "auto"
      },
      "pluginVersion": "9.3.6",
      "targets": [
        {
          "datasource": {
            "type": "prometheus",
            "uid": "${datasource}"
          },
          "editorMode": "code",
          "expr": "sort(round(gobot_bme280_sensor_humidity_percent{location=\"dd\"}))",
          "legendFormat": "{{placement}}",
          "range": true,
          "refId": "A"
        }
      ],
      "title": "Humidity DD",
      "type": "stat"
    },
    {
      "datasource": {
        "type": "prometheus",
        "uid": "${datasource}"
      },
      "fieldConfig": {
        "defaults": {
          "color": {
            "mode": "thresholds"
          },
          "mappings": [],
          "max": 100,
          "min": 0,
          "thresholds": {
            "mode": "absolute",
            "steps": [
              {
                "color": "dark-purple",
                "value": null
              },
              {
                "color": "semi-dark-purple",
                "value": 25
              },
              {
                "color": "purple",
                "value": 50
              },
              {
                "color": "super-light-purple",
                "value": 75
              }
            ]
          },
          "unit": "humidity"
        },
        "overrides": []
      },
      "gridPos": {
        "h": 4,
        "w": 8,
        "x": 8,
        "y": 23
      },
      "id": 59,
      "options": {
        "orientation": "auto",
        "reduceOptions": {
          "calcs": [
            "last"
          ],
          "fields": "",
          "values": false
        },
        "showThresholdLabels": false,
        "showThresholdMarkers": true
      },
      "pluginVersion": "9.3.6",
      "targets": [
        {
          "datasource": {
            "type": "prometheus",
            "uid": "${datasource}"
          },
          "editorMode": "code",
          "expr": "sort_desc(round(gobot_lux_sensor_brightness_level_percent))",
          "legendFormat": "{{placement}}",
          "range": true,
          "refId": "A"
        }
      ],
      "title": "Lux DD",
      "type": "gauge"
    },
    {
      "datasource": {
        "type": "prometheus",
        "uid": "${datasource}"
      },
      "fieldConfig": {
        "defaults": {
          "color": {
            "mode": "thresholds"
          },
          "mappings": [],
          "max": 30,
          "min": 13,
          "thresholds": {
            "mode": "absolute",
            "steps": [
              {
                "color": "super-light-blue",
                "value": null
              },
              {
                "color": "blue",
                "value": 16
              },
              {
                "color": "green",
                "value": 20
              },
              {
                "color": "red",
                "value": 26
              },
              {
                "color": "dark-red",
                "value": 32
              }
            ]
          },
          "unit": "celsius"
        },
        "overrides": []
      },
      "gridPos": {
        "h": 4,
        "w": 4,
        "x": 16,
        "y": 23
      },
      "id": 37,
      "options": {
        "colorMode": "background",
        "graphMode": "area",
        "justifyMode": "auto",
        "orientation": "auto",
        "reduceOptions": {
          "calcs": [
            "last"
          ],
          "fields": "",
          "values": false
        },
        "textMode": "auto"
      },
      "pluginVersion": "9.3.6",
      "targets": [
        {
          "datasource": {
            "type": "prometheus",
            "uid": "${datasource}"
          },
          "editorMode": "code",
          "expr": "sort(avg_over_time(gobot_bme280_sensor_temperature_celsius{location=\"pt\"}[1h]))",
          "legendFormat": "{{placement}}",
          "range": true,
          "refId": "A"
        }
      ],
      "title": "Temperature PT",
      "type": "stat"
    },
    {
      "datasource": {
        "type": "prometheus",
        "uid": "${datasource}"
      },
      "fieldConfig": {
        "defaults": {
          "color": {
            "mode": "thresholds"
          },
          "mappings": [],
          "max": 80,
          "min": 20,
          "thresholds": {
            "mode": "absolute",
            "steps": [
              {
                "color": "red",
                "value": null
              },
              {
                "color": "green",
                "value": 25
              },
              {
                "color": "red",
                "value": 75
              }
            ]
          },
          "unit": "humidity"
        },
        "overrides": []
      },
      "gridPos": {
        "h": 4,
        "w": 4,
        "x": 20,
        "y": 23
      },
      "id": 38,
      "options": {
        "colorMode": "background",
        "graphMode": "area",
        "justifyMode": "auto",
        "orientation": "auto",
        "reduceOptions": {
          "calcs": [
            "last"
          ],
          "fields": "",
          "values": false
        },
        "textMode": "auto"
      },
      "pluginVersion": "9.3.6",
      "targets": [
        {
          "datasource": {
            "type": "prometheus",
            "uid": "${datasource}"
          },
          "editorMode": "code",
          "expr": "sort(round(gobot_bme280_sensor_humidity_percent{location=\"pt\"}))",
          "legendFormat": "{{placement}}",
          "range": true,
          "refId": "A"
        }
      ],
      "title": "Humidity PT",
      "type": "stat"
    },
    {
      "collapsed": false,
      "gridPos": {
        "h": 1,
        "w": 24,
        "x": 0,
        "y": 27
      },
      "id": 29,
      "panels": [],
      "title": "Hardware",
      "type": "row"
    },
    {
      "datasource": {
        "type": "prometheus",
        "uid": "${datasource}"
      },
      "fieldConfig": {
        "defaults": {
          "color": {
            "mode": "thresholds"
          },
          "mappings": [],
          "thresholds": {
            "mode": "absolute",
            "steps": [
              {
                "color": "green",
                "value": null
              },
              {
                "color": "yellow",
                "value": 80
              },
              {
                "color": "red",
                "value": 90
              }
            ]
          },
          "unit": "celsius"
        },
        "overrides": []
      },
      "gridPos": {
        "h": 4,
        "w": 6,
        "x": 0,
        "y": 28
      },
      "id": 27,
      "options": {
        "colorMode": "background",
        "graphMode": "area",
        "justifyMode": "auto",
        "orientation": "auto",
        "reduceOptions": {
          "calcs": [
            "last"
          ],
          "fields": "",
          "values": false
        },
        "textMode": "auto"
      },
      "pluginVersion": "9.3.6",
      "targets": [
        {
          "datasource": {
            "type": "prometheus",
            "uid": "${datasource}"
          },
          "editorMode": "code",
          "expr": "round(quantile(0.95, max_over_time(node_hwmon_temp_celsius{chip!~\"^nvme.*\"}[5m])) by (location))",
          "legendFormat": "__auto",
          "range": true,
          "refId": "A"
        }
      ],
      "title": "Max CPU Temp 5m",
      "type": "stat"
    },
    {
      "datasource": {
        "type": "prometheus",
        "uid": "${datasource}"
      },
      "fieldConfig": {
        "defaults": {
          "color": {
            "mode": "thresholds"
          },
          "mappings": [],
          "thresholds": {
            "mode": "absolute",
            "steps": [
              {
                "color": "green",
                "value": null
              },
              {
                "color": "#EAB839",
                "value": 65
              },
              {
                "color": "red",
                "value": 70
              }
            ]
          },
          "unit": "celsius"
        },
        "overrides": []
      },
      "gridPos": {
        "h": 4,
        "w": 6,
        "x": 6,
        "y": 28
      },
      "id": 6,
      "options": {
        "colorMode": "background",
        "graphMode": "area",
        "justifyMode": "auto",
        "orientation": "auto",
        "reduceOptions": {
          "calcs": [
            "last"
          ],
          "fields": "",
          "values": false
        },
        "textMode": "auto"
      },
      "pluginVersion": "9.3.6",
      "targets": [
        {
          "datasource": {
            "type": "prometheus",
            "uid": "${datasource}"
          },
          "editorMode": "code",
          "expr": "round(quantile(0.99, max_over_time(node_hwmon_temp_celsius{chip=~\"^nvme.*\"}[5m])) by (location))",
          "legendFormat": "__auto",
          "range": true,
          "refId": "A"
        }
      ],
      "title": "Max Disk Temp",
      "type": "stat"
    },
    {
      "datasource": {
        "type": "prometheus",
        "uid": "${datasource}"
      },
      "fieldConfig": {
        "defaults": {
          "color": {
            "mode": "thresholds"
          },
          "mappings": [],
          "max": 100,
          "min": 0,
          "thresholds": {
            "mode": "absolute",
            "steps": [
              {
                "color": "red",
                "value": null
              },
              {
                "color": "#EAB839",
                "value": 15
              },
              {
                "color": "green",
                "value": 30
              }
            ]
          },
          "unit": "percent"
        },
        "overrides": []
      },
      "gridPos": {
        "h": 4,
        "w": 2,
        "x": 12,
        "y": 28
      },
      "id": 36,
      "options": {
        "colorMode": "background",
        "graphMode": "area",
        "justifyMode": "auto",
        "orientation": "auto",
        "reduceOptions": {
          "calcs": [
            "last"
          ],
          "fields": "",
          "values": false
        },
        "textMode": "auto"
      },
      "pluginVersion": "9.3.6",
      "targets": [
        {
          "datasource": {
            "type": "prometheus",
            "uid": "${datasource}"
          },
          "editorMode": "code",
          "expr": "min(node_filesystem_free_bytes{fstype=~\"ext4|xfs|vfat|tmpfs\"} * 100 / node_filesystem_size_bytes{fstype=~\"ext4|xfs|vfat|tmpfs\"})",
          "legendFormat": "__auto",
          "range": true,
          "refId": "A"
        }
      ],
      "title": "Min Free Disk",
      "type": "stat"
    },
    {
      "datasource": {
        "type": "prometheus",
        "uid": "${datasource}"
      },
      "fieldConfig": {
        "defaults": {
          "color": {
            "mode": "thresholds"
          },
          "mappings": [],
          "max": 100,
          "min": 0,
          "thresholds": {
            "mode": "absolute",
            "steps": [
              {
                "color": "green",
                "value": null
              },
              {
                "color": "orange",
                "value": 75
              },
              {
                "color": "red",
                "value": 90
              }
            ]
          },
          "unit": "percent"
        },
        "overrides": []
      },
      "gridPos": {
        "h": 4,
        "w": 2,
        "x": 14,
        "y": 28
      },
      "id": 68,
      "options": {
        "colorMode": "background",
        "graphMode": "area",
        "justifyMode": "auto",
        "orientation": "auto",
        "reduceOptions": {
          "calcs": [
            "last"
          ],
          "fields": "",
          "values": false
        },
        "textMode": "auto"
      },
      "pluginVersion": "9.3.6",
      "targets": [
        {
          "datasource": {
            "type": "prometheus",
            "uid": "${datasource}"
          },
          "editorMode": "code",
          "expr": "max(100 * (1 - (node_memory_MemFree_bytes + node_memory_Cached_bytes + node_memory_Buffers_bytes) / node_memory_MemTotal_bytes))",
          "legendFormat": "__auto",
          "range": true,
          "refId": "A"
        }
      ],
      "title": "Max Ram Usage",
      "type": "stat"
    },
    {
      "datasource": {
        "type": "prometheus",
        "uid": "${datasource}"
      },
      "fieldConfig": {
        "defaults": {
          "color": {
            "mode": "thresholds"
          },
          "mappings": [],
          "max": 1,
          "min": 0,
          "thresholds": {
            "mode": "absolute",
            "steps": [
              {
                "color": "green",
                "value": null
              },
              {
                "color": "orange",
                "value": 75
              },
              {
                "color": "red",
                "value": 90
              }
            ]
          },
          "unit": "percentunit"
        },
        "overrides": []
      },
      "gridPos": {
        "h": 4,
        "w": 2,
        "x": 16,
        "y": 28
      },
      "id": 69,
      "options": {
        "colorMode": "background",
        "graphMode": "area",
        "justifyMode": "auto",
        "orientation": "auto",
        "reduceOptions": {
          "calcs": [
            "last"
          ],
          "fields": "",
          "values": false
        },
        "textMode": "auto"
      },
      "pluginVersion": "9.3.6",
      "targets": [
        {
          "datasource": {
            "type": "prometheus",
            "uid": "${datasource}"
          },
          "editorMode": "code",
          "expr": "max(1 - avg(irate(node_cpu_seconds_total{mode=\"idle\"}[10m])) by (instance))",
          "legendFormat": "__auto",
          "range": true,
          "refId": "A"
        }
      ],
      "title": "Max CPU Usage",
      "type": "stat"
    },
    {
      "collapsed": false,
      "gridPos": {
        "h": 1,
        "w": 24,
        "x": 0,
        "y": 32
      },
      "id": 66,
      "panels": [],
      "title": "Christmas Tree",
      "type": "row"
    },
    {
      "datasource": {
        "type": "prometheus",
        "uid": "${datasource}"
      },
      "fieldConfig": {
        "defaults": {
          "color": {
            "mode": "thresholds"
          },
          "custom": {
            "align": "auto",
            "displayMode": "auto",
            "inspect": false
          },
          "mappings": [],
          "thresholds": {
            "mode": "absolute",
            "steps": [
              {
                "color": "green",
                "value": null
              },
              {
                "color": "red",
                "value": 80
              }
            ]
          }
        },
        "overrides": [
          {
            "matcher": {
              "id": "byName",
              "options": "alertname"
            },
            "properties": [
              {
                "id": "custom.width",
                "value": 536
              }
            ]
          }
        ]
      },
      "gridPos": {
        "h": 6,
        "w": 12,
        "x": 0,
        "y": 33
      },
      "id": 40,
      "options": {
        "footer": {
          "fields": "",
          "reducer": [
            "sum"
          ],
          "show": false
        },
        "showHeader": true,
        "sortBy": []
      },
      "pluginVersion": "9.3.6",
      "targets": [
        {
          "datasource": {
            "type": "prometheus",
            "uid": "${datasource}"
          },
          "editorMode": "code",
          "exemplar": false,
          "expr": "sort_desc(sum(vmalert_alerts_firing{alertname!=\"Dead Man's Switch\"}> 0 or ALERTS > 0) by (alertname) / 3)",
          "format": "table",
          "instant": true,
          "legendFormat": "__auto",
          "range": false,
          "refId": "A"
        }
      ],
      "title": "Active Alerts",
      "transformations": [
        {
          "id": "organize",
          "options": {
            "excludeByName": {
              "Time": true
            },
            "indexByName": {},
            "renameByName": {}
          }
        }
      ],
      "type": "table"
    },
    {
      "datasource": {
        "type": "prometheus",
        "uid": "${datasource}"
      },
      "fieldConfig": {
        "defaults": {
          "color": {
            "mode": "thresholds"
          },
          "custom": {
            "align": "auto",
            "displayMode": "auto",
            "inspect": false
          },
          "mappings": [],
          "thresholds": {
            "mode": "absolute",
            "steps": [
              {
                "color": "green",
                "value": null
              },
              {
                "color": "red",
                "value": 80
              }
            ]
          }
        },
        "overrides": [
          {
            "matcher": {
              "id": "byName",
              "options": "alertname"
            },
            "properties": [
              {
                "id": "custom.width",
                "value": 536
              }
            ]
          }
        ]
      },
      "gridPos": {
        "h": 6,
        "w": 12,
        "x": 12,
        "y": 33
      },
      "id": 64,
      "options": {
        "footer": {
          "fields": "",
          "reducer": [
            "sum"
          ],
          "show": false
        },
        "showHeader": true,
        "sortBy": []
      },
      "pluginVersion": "9.3.6",
      "targets": [
        {
          "datasource": {
            "type": "prometheus",
            "uid": "${datasource}"
          },
          "editorMode": "code",
          "exemplar": false,
          "expr": "sort_desc(sum(vmalert_alerts_pending > 0 or ALERTS > 0) by (alertname) / 3)",
          "format": "table",
          "instant": true,
          "legendFormat": "__auto",
          "range": false,
          "refId": "A"
        }
      ],
      "title": "Pending",
      "transformations": [
        {
          "id": "organize",
          "options": {
            "excludeByName": {
              "Time": true
            },
            "indexByName": {},
            "renameByName": {}
          }
        }
      ],
      "type": "table"
    }
  ],
  "refresh": "1m",
  "schemaVersion": 37,
  "style": "dark",
  "tags": [],
  "templating": {
    "list": [
      {
        "current": {
          "selected": false,
          "text": "Prometheus",
          "value": "Prometheus"
        },
        "hide": 2,
        "includeAll": false,
        "label": "Datasource",
        "multi": false,
        "name": "datasource",
        "options": [],
        "query": "prometheus",
        "refresh": 1,
        "regex": "",
        "skipUrlSync": false,
        "type": "datasource"
      }
    ]
  },
  "time": {
    "from": "now-2d",
    "to": "now"
  },
  "timepicker": {},
  "timezone": "",
  "title": "Overview",
  "uid": "SSyiU3pVk",
  "version": 1,
  "weekStart": ""
}